incribo/__init__.py
incribo/test.py
incribo/test_emb_streamer.py
incribo-0.1.2.dist-info/LICENSE
incribo-0.1.2.dist-info/METADATA
incribo-0.1.2.dist-info/WHEEL
incribo-0.1.2.dist-info/top_level.txt
incribo-0.1.2.dist-info/RECORD
