Metadata-Version: 2.1
Name: incribo
Version: 0.1.2
Summary: Generate stateful embeddings for your AI
Author: Uma Venugopal
Author-email: uma@incribo.com
Classifier: Programming Language :: Python :: 3
Classifier: License :: OSI Approved :: Apache Software License
Classifier: Operating System :: OS Independent
Requires-Python: >=3.9
License-File: LICENSE
Requires-Dist: numpy>=1.9.0
Requires-Dist: matplotlib>=3.9.1
Requires-Dist: sentence-transformers>=3.0.1
Requires-Dist: torch>=2.4.0
Requires-Dist: incribo>=0.1.2
Provides-Extra: dev
Requires-Dist: pytest>=8.3.2; extra == "dev"
Requires-Dist: twine>=5.1.1; extra == "dev"
